MParkerO/__init__.py
MParkerO/interfacetovgg.py
MParkerO/plt_tools.py
MParkerO/vggtointerface.py
MParkerO-0.0.1.dist-info/LICENSE
MParkerO-0.0.1.dist-info/METADATA
MParkerO-0.0.1.dist-info/WHEEL
MParkerO-0.0.1.dist-info/top_level.txt
MParkerO-0.0.1.dist-info/RECORD
