Metadata-Version: 2.1
Name: MParkerO
Version: 0.0.1
Summary: A Python-Based Implementation of the Extended Parker-Oldenburg Algorithm                  for Inverting Multilayer Density Interfacesfrom Gravity Anomalies
Author: ZengJH
Author-email: z1714833751@163.com
Requires-Python: >=3.6
License-File: LICENSE
